smart_parallelize/__init__.py
smart_parallelize/parallelize.py
smart_parallelize/parallelize_native.py
smart_parallelize-2.3.5.dist-info/METADATA
smart_parallelize-2.3.5.dist-info/WHEEL
smart_parallelize-2.3.5.dist-info/RECORD
