Metadata-Version: 2.1
Name: smart-parallelize
Version: 2.3.5
Summary: 
Author: Truman DeWalch
Author-email: trumandewalch@gmail.com
Requires-Python: >=3.10,<4.0
Classifier: Programming Language :: Python :: 3
Classifier: Programming Language :: Python :: 3.10
Classifier: Programming Language :: Python :: 3.11
Classifier: Programming Language :: Python :: 3.12
Requires-Dist: numpy (>=1.26.4,<2.0.0)
Requires-Dist: pathos (>=0.3.2,<0.4.0)
Requires-Dist: ray (>=2.10.0,<3.0.0)
